criticmarkup/__init__.py
criticmarkup/cli.py
criticmarkup/core.py
criticmarkup/presets.py
criticmarkup-0.1.1.dist-info/METADATA
criticmarkup-0.1.1.dist-info/WHEEL
criticmarkup-0.1.1.dist-info/entry_points.txt
criticmarkup-0.1.1.dist-info/RECORD
