Metadata-Version: 2.4
Name: criticmarkup
Version: 0.1.1
Summary: Fast CriticMarkup preprocessor with multiple output formats.
Keywords: asciidoc,criticmarkup,latex,markdown,preprocessor
Classifier: Environment :: Console
Classifier: Intended Audience :: Developers
Classifier: Programming Language :: Python :: 3
Classifier: Programming Language :: Python :: 3 :: Only
Classifier: Programming Language :: Python :: 3.11
Classifier: Programming Language :: Python :: 3.12
Classifier: Programming Language :: Python :: 3.13
Classifier: Topic :: Text Processing :: Markup
Requires-Python: >=3.11
Requires-Dist: rich>=13.7.0
Requires-Dist: typer>=0.12.0
Provides-Extra: dev
Requires-Dist: build>=1.2.0; extra == 'dev'
Requires-Dist: pytest>=8.2.0; extra == 'dev'
Requires-Dist: ruff>=0.6.0; extra == 'dev'
Requires-Dist: twine>=5.1.0; extra == 'dev'
